artd_modules/__init__.py
artd_modules/admin.py
artd_modules/apps.py
artd_modules/models.py
artd_modules/signals.py
artd_modules/utils.py
artd_modules/locale/en/LC_MESSAGES/django.po
artd_modules/locale/es/LC_MESSAGES/django.po
artd_modules/migrations/0001_initial.py
artd_modules/migrations/0002_module_slug.py
artd_modules/migrations/__init__.py
modules/__init__.py
modules/asgi.py
modules/settings.py
modules/urls.py
modules/wsgi.py
artd_modules-1.0.6.dist-info/LICENSE
artd_modules-1.0.6.dist-info/METADATA
artd_modules-1.0.6.dist-info/WHEEL
artd_modules-1.0.6.dist-info/top_level.txt
artd_modules-1.0.6.dist-info/RECORD
